fixit/__init__.py
fixit/__main__.py
fixit/cli/__init__.py
fixit/cli/fix.py
fixit/cli/gen.py
fixit/cli/init.py
fixit/cli/main.py
fixit/cli/sec.py
fixit/cli/test.py
fixit/core/__init__.py
fixit/core/config.py
fixit/core/paths.py
fixit/explain/__init__.py
fixit/explain/advisor.py
fixit/explain/models.py
fixit/explain/patches.py
fixit/explain/prompts/__init__.py
fixit/explain/schemas/__init__.py
fixit/explain/schemas/v1/__init__.py
fixit/explain/schemas/v1/failure_advice.schema.json
fixit/explain/schemas/v1/security_findings.schema.json
fixit/gen/__init__.py
fixit/gen/cases.py
fixit/gen/writer.py
fixit/gen/templates/pytest_endpoint.j2
fixit/llm/__init__.py
fixit/llm/adapter.py
fixit/llm/cache.py
fixit/llm/backends/__init__.py
fixit/llm/backends/llama_cpp.py
fixit/llm/backends/lm_studio.py
fixit/llm/backends/ollama.py
fixit/run/__init__.py
fixit/run/reporter_html.py
fixit/run/reporter_rich.py
fixit/run/runner.py
fixit/sec/__init__.py
fixit/sec/checks.py
fixit/spec/__init__.py
fixit/spec/autodiscover.py
fixit/spec/fastapi_extract.py
fixit/spec/from_express.py
fixit/spec/from_fastapi.py
fixit/spec/loader.py
fixit/spec/models.py
fixit/spec/validator.py
fixit/utils/__init__.py
fixit/utils/http.py
fixit_ai-1.0.0.dist-info/licenses/LICENSE
fixit_ai-1.0.0.dist-info/METADATA
fixit_ai-1.0.0.dist-info/WHEEL
fixit_ai-1.0.0.dist-info/entry_points.txt
fixit_ai-1.0.0.dist-info/top_level.txt
fixit_ai-1.0.0.dist-info/RECORD
