Metadata-Version: 2.4
Name: fixit-ai
Version: 1.0.0
Summary: AI-Powered API Testing Agent with Zero-Config Onboarding for OpenAPI-First Development
Author: Ashish Prajapati, Gauri Baheti, Khushali Dukhande, Om Mohite
Maintainer-email: Ashiiish-88 <prajapatiashish661@gmail.com>, ommo007 <omamohite@gmail.com>
License-Expression: MIT
Project-URL: Homepage, https://github.com/Fixit-Local-AI-Agent/Fixit.AI
Project-URL: Documentation, https://github.com/Fixit-Local-AI-Agent/Fixit.AI/wiki
Project-URL: Repository, https://github.com/Fixit-Local-AI-Agent/Fixit.AI
Project-URL: Bug Tracker, https://github.com/Fixit-Local-AI-Agent/Fixit.AI/issues
Project-URL: Discussions, https://github.com/Fixit-Local-AI-Agent/Fixit.AI/discussions
Project-URL: Changelog, https://github.com/Fixit-Local-AI-Agent/Fixit.AI/blob/main/CHANGELOG.md
Project-URL: Source Code, https://github.com/Fixit-Local-AI-Agent/Fixit.AI
Keywords: api,testing,openapi,fastapi,express,ai,llm,security,automation,testing-framework,hackathon,offline,local-llm,chatgpt-oss
Classifier: Development Status :: 4 - Beta
Classifier: Intended Audience :: Developers
Classifier: Topic :: Software Development :: Testing
Classifier: Topic :: Software Development :: Quality Assurance
Classifier: Topic :: Internet :: WWW/HTTP :: HTTP Servers
Classifier: Topic :: Scientific/Engineering :: Artificial Intelligence
Classifier: Programming Language :: Python :: 3
Classifier: Programming Language :: Python :: 3.11
Classifier: Programming Language :: Python :: 3.12
Classifier: Programming Language :: Python :: 3.13
Classifier: Operating System :: OS Independent
Classifier: Environment :: Console
Classifier: Framework :: FastAPI
Classifier: Framework :: Pytest
Requires-Python: >=3.11
License-File: LICENSE
Requires-Dist: typer[all]<0.17,>=0.12.3
Requires-Dist: rich<15.0,>=13.7
Requires-Dist: httpx<0.29,>=0.27
Requires-Dist: requests>=2.31.0
Requires-Dist: urllib3>=2.0.0
Requires-Dist: pytest<9.0,>=8.3
Requires-Dist: jinja2<4.0,>=3.1
Requires-Dist: pydantic<3.0,>=2.7
Requires-Dist: prance<24.0,>=23.6.21
Requires-Dist: schemathesis<5.0,>=4.1.0
Requires-Dist: ruamel.yaml>=0.18.6
Requires-Dist: jsonschema>=4.22.0
Requires-Dist: tenacity>=8.2.0
Requires-Dist: unidiff>=0.7.5
Provides-Extra: dev
Requires-Dist: black>=24.4.2; extra == "dev"
Requires-Dist: ruff>=0.5.2; extra == "dev"
Requires-Dist: mypy>=1.10.0; extra == "dev"
Requires-Dist: pytest-cov>=6.0.0; extra == "dev"
Requires-Dist: pre-commit>=3.7.0; extra == "dev"
Requires-Dist: deptry>=0.16.1; extra == "dev"
Provides-Extra: examples
Requires-Dist: fastapi>=0.111.0; extra == "examples"
Requires-Dist: uvicorn>=0.30.0; extra == "examples"
Requires-Dist: pydantic[email]>=2.7.0; extra == "examples"
Provides-Extra: llm-providers
Requires-Dist: openai>=1.30.0; extra == "llm-providers"
Requires-Dist: ollama>=0.2.0; extra == "llm-providers"
Requires-Dist: llama-cpp-python>=0.2.77; extra == "llm-providers"
Provides-Extra: all
Requires-Dist: fixit-ai[dev,examples,llm-providers]; extra == "all"
Dynamic: license-file
